sale_subscription_automatic_post/__init__.py
sale_subscription_automatic_post/configuration.py
sale_subscription_automatic_post/configuration.xml
sale_subscription_automatic_post/subscription.py
sale_subscription_automatic_post/subscription.xml
sale_subscription_automatic_post/tryton.cfg
sale_subscription_automatic_post/locale/fr.po
sale_subscription_automatic_post/tests/__init__.py
sale_subscription_automatic_post/tests/conftest.py
sale_subscription_automatic_post/tests/test_automatic_post.py
sale_subscription_automatic_post/tests/test_default_invoice_state.py
sale_subscription_automatic_post/tests/test_module.py
sale_subscription_automatic_post/view/configuration_form.xml
sale_subscription_automatic_post/view/subscription_form.xml
hb_tryton_sale_subscription_automatic_post-1.0.0.dist-info/LICENSE
hb_tryton_sale_subscription_automatic_post-1.0.0.dist-info/METADATA
hb_tryton_sale_subscription_automatic_post-1.0.0.dist-info/WHEEL
hb_tryton_sale_subscription_automatic_post-1.0.0.dist-info/entry_points.txt
hb_tryton_sale_subscription_automatic_post-1.0.0.dist-info/top_level.txt
hb_tryton_sale_subscription_automatic_post-1.0.0.dist-info/RECORD
