Metadata-Version: 2.1
Name: hb-tryton-sale-subscription-automatic-post
Version: 1.0.0
Summary: Define in the sale subscription if the invoice must be posted or validated
Home-page: https://hashbang.fr/
Author: HashBang
Author-email: contact@hashbang.fr
License: GPL-3
Project-URL: Bug Tracker, https://gitlab.com/hashbangfr/tryton-modules/tryton_hb_sale_subscription_automatic_post/-/issues
Project-URL: Source Code, https://gitlab.com/hashbangfr/tryton-modules/tryton_hb_sale_subscription_automatic_post/
Classifier: Development Status :: 5 - Production/Stable
Classifier: Environment :: Plugins
Classifier: Framework :: Tryton
Classifier: Intended Audience :: Developers
Classifier: Intended Audience :: Financial and Insurance Industry
Classifier: Intended Audience :: Legal Industry
Classifier: License :: OSI Approved :: GNU General Public License v3 or later (GPLv3+)
Classifier: Natural Language :: English
Classifier: Natural Language :: French
Classifier: Operating System :: OS Independent
Classifier: Programming Language :: Python :: 3
Classifier: Programming Language :: Python :: 3.6
Classifier: Programming Language :: Python :: 3.7
Classifier: Programming Language :: Python :: 3.8
Classifier: Programming Language :: Python :: 3.9
Classifier: Programming Language :: Python :: Implementation :: CPython
Classifier: Programming Language :: Python :: Implementation :: PyPy
Classifier: Topic :: Office/Business
Requires-Python: >=3.6
License-File: LICENSE
Requires-Dist: wheel
Requires-Dist: tryton
Requires-Dist: trytond
Requires-Dist: trytond-sale-subscription
